exonutils/__init__.py
exonutils/buffers/__init__.py
exonutils/buffers/common.py
exonutils/buffers/filebuffer.py
exonutils/buffers/shareddata.py
exonutils/fileconfig/__init__.py
exonutils/fileconfig/blobconfig.py
exonutils/fileconfig/common.py
exonutils/fileconfig/jsonconfig.py
exonutils/process/__init__.py
exonutils/process/daemon.py
exonutils/process/routine.py
exonutils/process/service.py
exonutils/services/__init__.py
exonutils/services/ftp.py
exonutils/services/ftp_shell.py
exonutils/utils/__init__.py
exonutils/utils/console.py
exonutils/utils/pipe.py
exonutils/utils/pkgtools.py
exonutils/utils/shell.py
exonutils/utils/validation.py
exonutils-7.1.dist-info/LICENSE.txt
exonutils-7.1.dist-info/METADATA
exonutils-7.1.dist-info/WHEEL
exonutils-7.1.dist-info/top_level.txt
exonutils-7.1.dist-info/RECORD
