Metadata-Version: 2.1
Name: exonutils
Version: 7.1
Summary: General tools and utils for applications.
Author-email: ExonLabs <info@exonlabs.net>
License: BSD 3-Clause License
Project-URL: Documentation, https://exonlabs.github.io/py-exonutils
Project-URL: Repository, https://github.com/exonlabs/py-exonutils
Classifier: Development Status :: 5 - Production/Stable
Classifier: Intended Audience :: Developers
Classifier: License :: OSI Approved :: BSD License
Classifier: Operating System :: OS Independent
Classifier: Programming Language :: Python
Classifier: Programming Language :: Python :: 3.9
Classifier: Programming Language :: Python :: 3.10
Classifier: Programming Language :: Python :: 3.11
Classifier: Programming Language :: Python :: 3.12
Classifier: Topic :: Software Development :: Libraries
Classifier: Topic :: Software Development :: Libraries :: Python Modules
Requires-Python: >=3.9
License-File: LICENSE.txt
Requires-Dist: colorama <1.0,>=0.4
Requires-Dist: setproctitle <2.0,>=1.3
Provides-Extra: dev
